odoo/addons/account_banking_ach_direct_debit/README.rst
odoo/addons/account_banking_ach_direct_debit/__init__.py
odoo/addons/account_banking_ach_direct_debit/__manifest__.py
odoo/addons/account_banking_ach_direct_debit/post_install.py
odoo/addons/account_banking_ach_direct_debit/data/account_payment_method.xml
odoo/addons/account_banking_ach_direct_debit/data/mandate_expire_cron.xml
odoo/addons/account_banking_ach_direct_debit/demo/ach_direct_debit_demo.xml
odoo/addons/account_banking_ach_direct_debit/i18n/account_banking_ach_direct_debit.pot
odoo/addons/account_banking_ach_direct_debit/models/__init__.py
odoo/addons/account_banking_ach_direct_debit/models/account_banking_mandate.py
odoo/addons/account_banking_ach_direct_debit/models/account_payment_order.py
odoo/addons/account_banking_ach_direct_debit/readme/CONFIGURE.rst
odoo/addons/account_banking_ach_direct_debit/readme/CONTRIBUTORS.rst
odoo/addons/account_banking_ach_direct_debit/readme/DESCRIPTION.rst
odoo/addons/account_banking_ach_direct_debit/readme/INSTALL.rst
odoo/addons/account_banking_ach_direct_debit/readme/USAGE.rst
odoo/addons/account_banking_ach_direct_debit/static/description/icon.png
odoo/addons/account_banking_ach_direct_debit/static/description/index.html
odoo/addons/account_banking_ach_direct_debit/tests/__init__.py
odoo/addons/account_banking_ach_direct_debit/tests/test_account_payment.py
odoo/addons/account_banking_ach_direct_debit/tests/test_mandate.py
odoo/addons/account_banking_ach_direct_debit/views/account_banking_mandate_view.xml
odoo/addons/account_banking_ach_direct_debit/views/account_payment_order.xml
odoo14_addon_account_banking_ach_direct_debit-14.0.1.0.1.dev6.dist-info/METADATA
odoo14_addon_account_banking_ach_direct_debit-14.0.1.0.1.dev6.dist-info/WHEEL
odoo14_addon_account_banking_ach_direct_debit-14.0.1.0.1.dev6.dist-info/top_level.txt
odoo14_addon_account_banking_ach_direct_debit-14.0.1.0.1.dev6.dist-info/RECORD
